Metadata-Version: 2.1
Name: TkFast
Version: 0.1.1
Summary: 这个是Tkinter的快捷指令，做Tk时，能使你效率加倍！
Home-page: https://github.com/
Author: Yanming Guo
Author-email: gyms1111@163.com
License: UNKNOWN
Platform: UNKNOWN
Classifier: Programming Language :: Python :: 3
Classifier: License :: OSI Approved :: MIT License
Classifier: Operating System :: OS Independent
